.gitignore
MANIFEST.in
README.md
setup.cfg
setup.py
fava_inventory/__init__.py
fava_inventory.egg-info/PKG-INFO
fava_inventory.egg-info/SOURCES.txt
fava_inventory.egg-info/dependency_links.txt
fava_inventory.egg-info/not-zip-safe
fava_inventory.egg-info/requires.txt
fava_inventory.egg-info/top_level.txt
fava_inventory/templates/InventoryList.html