Metadata-Version: 2.1
Name: fava-inventory
Version: 0.1.0
Summary: Fava extension for beancount physical inventory balances
Home-page: https://github.com/ROCHK/fava_inventory
Author: Ronald Cheng
Author-email: ROCHK@users.noreply.github.com
License: GPL-3.0
Keywords: fava beancount inventory management
Platform: UNKNOWN
Classifier: Development Status :: 3 - Alpha
Classifier: Intended Audience :: Financial and Insurance Industry
Classifier: License :: OSI Approved :: GNU General Public License v3 (GPLv3)
Classifier: Natural Language :: English
Classifier: Programming Language :: Python :: 3 :: Only
Classifier: Programming Language :: Python :: 3.6
Classifier: Topic :: Internet :: WWW/HTTP :: Dynamic Content
Classifier: Topic :: Office/Business :: Financial :: Accounting
